Metadata-Version: 2.4
Name: sphinx-llms-txt
Version: 0.7.1
Summary: llms-full.txt generator for Sphinx
Author-email: Jared Dillard <jared.dillard@gmail.com>
Maintainer-email: Jared Dillard <jared.dillard@gmail.com>
License: MIT
Project-URL: download, https://pypi.org/project/sphinx-llms-txt/
Project-URL: source, https://github.com/jdillard/sphinx-llms-txt
Project-URL: changelog, https://github.com/jdillard/sphinx-llms-txt/blob/master/CHANGELOG.rst
Classifier: Framework :: Sphinx :: Extension
Classifier: License :: OSI Approved :: MIT License
Classifier: Programming Language :: Python :: 3.9
Classifier: Programming Language :: Python :: 3.10
Classifier: Programming Language :: Python :: 3.11
Classifier: Programming Language :: Python :: 3.12
Classifier: Topic :: Documentation :: Sphinx
License-File: LICENSE
Requires-Dist: sphinx
Dynamic: license-file
